makeitpop/__init__.py
makeitpop/derivatives.py
makeitpop/makeitpop.py
makeitpop-0.1.dist-info/LICENSE
makeitpop-0.1.dist-info/WHEEL
makeitpop-0.1.dist-info/METADATA
makeitpop-0.1.dist-info/RECORD
