Metadata-Version: 2.1
Name: makeitpop
Version: 0.1
Summary: Warp your data using the same perceptual warping that Jet applies!
Home-page: https://github.com/choldgraf/makeitpop
License: UNKNOWN
Author: Chris Holdgraf
Author-email: choldgraf@berkeley.edu
Classifier: License :: OSI Approved :: MIT License
